pymd_editor/__init__.py
pymd_editor/__main__.py
pymd_editor/pymd_editor_constants.py
pymd_editor/pymd_editor_frame.py
pymd_editor/pymd_editor_window.py
pymd_editor-0.0.4.dist-info/LICENSE
pymd_editor-0.0.4.dist-info/LICENSE.txt
pymd_editor-0.0.4.dist-info/METADATA
pymd_editor-0.0.4.dist-info/WHEEL
pymd_editor-0.0.4.dist-info/entry_points.txt
pymd_editor-0.0.4.dist-info/top_level.txt
pymd_editor-0.0.4.dist-info/RECORD
