Metadata-Version: 2.1
Name: pymd-editor
Version: 0.0.4
Summary: A Python based Markdown editor with HTML preview
Home-page: https://github.com/hreikin/pymd-editor
Author: hreikin
Author-email: hreikin@gmail.com
License: MIT
Platform: UNKNOWN
Classifier: License :: OSI Approved :: MIT License
Classifier: Programming Language :: Python :: 3
Classifier: Programming Language :: Python :: 3.7
License-File: LICENSE
License-File: LICENSE.txt
Requires-Dist: markdown
Requires-Dist: pygments
Requires-Dist: tkinterweb
Requires-Dist: ttkbootstrap
